cmdflow_CLI/CLI.py
cmdflow_CLI/__init__.py
cmdflow_CLI/__main__.py
cmdflow_CLI/cmdflow_allfunc.py
cmdflow_CLI-0.1.1.dist-info/METADATA
cmdflow_CLI-0.1.1.dist-info/WHEEL
cmdflow_CLI-0.1.1.dist-info/entry_points.txt
cmdflow_CLI-0.1.1.dist-info/top_level.txt
cmdflow_CLI-0.1.1.dist-info/RECORD
