Metadata-Version: 2.1
Name: cmdflow_CLI
Version: 0.1.1
Summary: A CLI tool for system monitoring, making plot charts and etc.
Author: Raunak
Classifier: Programming Language :: Python :: 3
Classifier: Operating System :: OS Independent
Requires-Python: >=3.6
Requires-Dist: rich
Requires-Dist: pyfiglet
Requires-Dist: matplotlib
Requires-Dist: asyncio
Requires-Dist: psutil
